id_tracker/__init__.py
id_tracker/admin.py
id_tracker/models.py
id_tracker/views.py
id_tracker/config/__init__.py
id_tracker/config/asgi.py
id_tracker/config/settings.py
id_tracker/config/urls.py
id_tracker/config/utilities.py
id_tracker/config/wsgi.py
id_tracker/firebase_auth/__init__.py
id_tracker/firebase_auth/firebase_authentication.py
id_tracker/firebase_auth/firebase_exceptions.py
id_tracker-0.0.1.dist-info/licenses/LICENSE
id_tracker-0.0.1.dist-info/METADATA
id_tracker-0.0.1.dist-info/WHEEL
id_tracker-0.0.1.dist-info/top_level.txt
id_tracker-0.0.1.dist-info/RECORD
